{
  "": "",
  "COLLAPSE": "",
  "LOADING": "",
  "Language": "",
  "LogIn": "",
  "Lorem ipsum dolor sit amet consectetur adipisicing elit": {
    " Eligendi": "",
    " EligendiLorem ipsum dolor sit amet consectetur adipisicing elit": {
      " EligendiLorem ipsum dolor sit amet consectetur adipisicing elit": {
        " Eligendi": ""
      }
    }
  },
  "ShortLanguage": "",
  "aboutPageBTN": "",
  "aboutPageText": "",
  "mainPageBTN": "",
  "mainPageText": "",
  "notFoundPage": "",
  "pageError": ""
}
